homebot/__init__.py
homebot/__main__.py
homebot/core/binder.py
homebot/core/bot.py
homebot/core/config.py
homebot/core/database.py
homebot/core/error_handler.py
homebot/core/logging.py
homebot/core/mdlintf.py
homebot/lib/libadmin/__init__.py
homebot/lib/libmdlintf/__init__.py
homebot/lib/libupload/__init__.py
homebot/main.py
homebot/modules/ci/__init__.py
homebot/modules/ci/artifacts.py
homebot/modules/ci/main.py
homebot/modules/ci/manager.py
homebot/modules/ci/parser.py
homebot/modules/ci/projects/aosp/post.py
homebot/modules/ci/projects/aosp/project.py
homebot/modules/ci/projects/aosp/returncode.py
homebot/modules/ci/projects/aosp/tools/building.sh
homebot/modules/ci/projects/lineageos-r/__init__.py
homebot/modules/ci/projects/lineageos-s/__init__.py
homebot/modules/ci/projects/twrpdtgen/__init__.py
homebot/modules/core/__init__.py
homebot/modules/core/main.py
homebot/modules/lineageos_updates/__init__.py
homebot/modules/lineageos_updates/device_data.py
homebot/modules/lineageos_updates/main.py
homebot/modules/lineageos_updates/observer.py
homebot/modules/lineageos_updates/poster.py
homebot/modules/shell/__init__.py
homebot/modules/shell/main.py
homebot/modules/speedtest/__init__.py
homebot/modules/speedtest/main.py
homebot/modules/xda/__init__.py
homebot/modules/xda/main.py
homebot/modules/xda/words.py
homebot-5.0.0.dist-info/WHEEL
homebot-5.0.0.dist-info/METADATA
homebot-5.0.0.dist-info/RECORD
