Metadata-Version: 2.1
Name: homebot
Version: 5.0.0
Summary: A Telegram bot written in Python
Author: Sebastiano Barezzi
Author-email: barezzisebastiano@gmail.com
Requires-Python: >=3.9,<4.0
Classifier: Programming Language :: Python :: 3
Classifier: Programming Language :: Python :: 3.10
Classifier: Programming Language :: Python :: 3.9
Requires-Dist: GitPython (>=3.1.24,<4.0.0)
Requires-Dist: PyGithub (>=1.55,<2.0)
Requires-Dist: PyYAML (>=6.0,<7.0)
Requires-Dist: natsort (>=8.0.0,<9.0.0)
Requires-Dist: paramiko (>=2.8.0,<3.0.0)
Requires-Dist: python-telegram-bot (>=13.7,<14.0)
Requires-Dist: requests (>=2.26.0,<3.0.0)
Requires-Dist: speedtest-cli (>=2.1.3,<3.0.0)
Requires-Dist: sphinx-rtd-theme (>=1.0.0,<2.0.0)
Requires-Dist: twrpdtgen (>=2.1.0,<3.0.0)
